<Humanoid name="HRP2">
  <Feet>	
    <Right>
	<SizeX> 0.2172 </SizeX>
	<SizeY> 0.138 </SizeY>
        <SizeZ> 0.105 </SizeZ>
        <AnklePosition> 0.059 0.0933 0.105 </AnklePosition>
    </Right>
    <Left>
	<SizeX> 0.2172 </SizeX>
	<SizeY> 0.138 </SizeY>
        <SizeZ> 0.105 </SizeZ>
        <AnklePosition>0.059 0.0933 0.105</AnklePosition>
    </Left>
  </Feet>	
  <Waist>
    <Right>
      <WaistToHip>0.0 -0.035 0.0</WaistToHip>
    </Right>
    <Left>
      <WaistToHip>0.0 0.035 0.0</WaistToHip>
    </Left>
  </Waist>
  <Legs>
    <Right>
        <FemurLength> 0.3 </FemurLength>
        <TibiaLength> 0.3 </TibiaLength>
    </Right>
    <Left>  
        <FemurLength>0.3</FemurLength>
        <TibiaLength> 0.3 </TibiaLegnth>
    </Left>
  </Legs>
  <Arms>
    <Right>
        <UpperArmLength> 0.25 </UpperArmLength>
        <ForeArmLength> 0.25 </ForeArmLength>
    </Right>
    <Left>
        <UpperArmLength> 0.25 </UpperArmLength>
        <ForeArmLength> 0.25 </ForeArmLength>
    </Left>
  </Arms>
</Humanoid>